AUTHORS.rst
CONTRIBUTING.rst
HISTORY.rst
LICENSE
MANIFEST.in
README.rst
setup.cfg
setup.py
docs/Makefile
docs/authors.rst
docs/conf.py
docs/contributing.rst
docs/history.rst
docs/index.rst
docs/installation.rst
docs/make.bat
docs/modules.rst
docs/readme.rst
docs/usage.rst
schemalite/__init__.py
schemalite/core.py
schemalite/validators.py
schemalite.egg-info/PKG-INFO
schemalite.egg-info/SOURCES.txt
schemalite.egg-info/dependency_links.txt
schemalite.egg-info/not-zip-safe
schemalite.egg-info/requires.txt
schemalite.egg-info/top_level.txt
tests/test_schemalite.py
tests/test_schemalite.py.bak