Metadata-Version: 1.1
Name: schemalite
Version: 0.2.1
Summary: A minimal, yet powerful schema validation library for python
Home-page: https://github.com/SuryaSankar/schemalite
Author: Surya Sankar
Author-email: suryashankar.m@gmail.com
License: MIT license
Keywords: schemalite
Platform: UNKNOWN
Classifier: Development Status :: 2 - Pre-Alpha
Classifier: Intended Audience :: Developers
Classifier: License :: OSI Approved :: MIT License
Classifier: Natural Language :: English
Classifier: Programming Language :: Python :: 2
Classifier: Programming Language :: Python :: 2.7
